logger_wrapper/__init__.py
logger_wrapper/logger_wrapper.py
logger_wrapper/scratch.py
logger_wrapper-0.1.0.dist-info/METADATA
logger_wrapper-0.1.0.dist-info/WHEEL
logger_wrapper-0.1.0.dist-info/top_level.txt
logger_wrapper-0.1.0.dist-info/RECORD
