Metadata-Version: 2.1
Name: logger-wrapper
Version: 0.1.0
Summary: The package wraps the built-in Logger package.  There are options to track from where the log message was created.
Download-URL: https://github.com/erolyesin/logger-wrapper/archive/refs/tags/v0.1.0.tar.gz
Author-email: Erol Yesin <erol@sandboxzilla.net>
Project-URL: Homepage, https://github.com/sandboxzilla/logger-wrapper
Project-URL: Bug Tracker, https://https://github.com/sandboxzilla/logger-wrapper/issues
Keywords: logger,logging,syslog,location,formating
Classifier: Development Status :: 4 - Beta
Classifier: Intended Audience :: Developers
Classifier: Topic :: Software Development :: Build Tools
Classifier: License :: OSI Approved :: MIT License
Classifier: Programming Language :: Python :: 3.11
Classifier: Operating System :: OS Independent
Requires-Python: >=3.11
